[
{
  "model": "auth.permission",
  "pk": 1,
  "fields": {
    "name": "Can add log entry",
    "content_type": 1,
    "codename": "add_logentry"
  }
},
{
  "model": "auth.permission",
  "pk": 2,
  "fields": {
    "name": "Can change log entry",
    "content_type": 1,
    "codename": "change_logentry"
  }
},
{
  "model": "auth.permission",
  "pk": 3,
  "fields": {
    "name": "Can delete log entry",
    "content_type": 1,
    "codename": "delete_logentry"
  }
},
{
  "model": "auth.permission",
  "pk": 4,
  "fields": {
    "name": "Can view log entry",
    "content_type": 1,
    "codename": "view_logentry"
  }
},
{
  "model": "auth.permission",
  "pk": 5,
  "fields": {
    "name": "Can add permission",
    "content_type": 2,
    "codename": "add_permission"
  }
},
{
  "model": "auth.permission",
  "pk": 6,
  "fields": {
    "name": "Can change permission",
    "content_type": 2,
    "codename": "change_permission"
  }
},
{
  "model": "auth.permission",
  "pk": 7,
  "fields": {
    "name": "Can delete permission",
    "content_type": 2,
    "codename": "delete_permission"
  }
},
{
  "model": "auth.permission",
  "pk": 8,
  "fields": {
    "name": "Can view permission",
    "content_type": 2,
    "codename": "view_permission"
  }
},
{
  "model": "auth.permission",
  "pk": 9,
  "fields": {
    "name": "Can add group",
    "content_type": 3,
    "codename": "add_group"
  }
},
{
  "model": "auth.permission",
  "pk": 10,
  "fields": {
    "name": "Can change group",
    "content_type": 3,
    "codename": "change_group"
  }
},
{
  "model": "auth.permission",
  "pk": 11,
  "fields": {
    "name": "Can delete group",
    "content_type": 3,
    "codename": "delete_group"
  }
},
{
  "model": "auth.permission",
  "pk": 12,
  "fields": {
    "name": "Can view group",
    "content_type": 3,
    "codename": "view_group"
  }
},
{
  "model": "auth.permission",
  "pk": 13,
  "fields": {
    "name": "Can add user",
    "content_type": 4,
    "codename": "add_user"
  }
},
{
  "model": "auth.permission",
  "pk": 14,
  "fields": {
    "name": "Can change user",
    "content_type": 4,
    "codename": "change_user"
  }
},
{
  "model": "auth.permission",
  "pk": 15,
  "fields": {
    "name": "Can delete user",
    "content_type": 4,
    "codename": "delete_user"
  }
},
{
  "model": "auth.permission",
  "pk": 16,
  "fields": {
    "name": "Can view user",
    "content_type": 4,
    "codename": "view_user"
  }
},
{
  "model": "auth.permission",
  "pk": 17,
  "fields": {
    "name": "Can add content type",
    "content_type": 5,
    "codename": "add_contenttype"
  }
},
{
  "model": "auth.permission",
  "pk": 18,
  "fields": {
    "name": "Can change content type",
    "content_type": 5,
    "codename": "change_contenttype"
  }
},
{
  "model": "auth.permission",
  "pk": 19,
  "fields": {
    "name": "Can delete content type",
    "content_type": 5,
    "codename": "delete_contenttype"
  }
},
{
  "model": "auth.permission",
  "pk": 20,
  "fields": {
    "name": "Can view content type",
    "content_type": 5,
    "codename": "view_contenttype"
  }
},
{
  "model": "auth.permission",
  "pk": 21,
  "fields": {
    "name": "Can add session",
    "content_type": 6,
    "codename": "add_session"
  }
},
{
  "model": "auth.permission",
  "pk": 22,
  "fields": {
    "name": "Can change session",
    "content_type": 6,
    "codename": "change_session"
  }
},
{
  "model": "auth.permission",
  "pk": 23,
  "fields": {
    "name": "Can delete session",
    "content_type": 6,
    "codename": "delete_session"
  }
},
{
  "model": "auth.permission",
  "pk": 24,
  "fields": {
    "name": "Can view session",
    "content_type": 6,
    "codename": "view_session"
  }
},
{
  "model": "auth.permission",
  "pk": 25,
  "fields": {
    "name": "Can add Город",
    "content_type": 7,
    "codename": "add_city"
  }
},
{
  "model": "auth.permission",
  "pk": 26,
  "fields": {
    "name": "Can change Город",
    "content_type": 7,
    "codename": "change_city"
  }
},
{
  "model": "auth.permission",
  "pk": 27,
  "fields": {
    "name": "Can delete Город",
    "content_type": 7,
    "codename": "delete_city"
  }
},
{
  "model": "auth.permission",
  "pk": 28,
  "fields": {
    "name": "Can view Город",
    "content_type": 7,
    "codename": "view_city"
  }
},
{
  "model": "auth.permission",
  "pk": 29,
  "fields": {
    "name": "Can add Клиент",
    "content_type": 8,
    "codename": "add_client"
  }
},
{
  "model": "auth.permission",
  "pk": 30,
  "fields": {
    "name": "Can change Клиент",
    "content_type": 8,
    "codename": "change_client"
  }
},
{
  "model": "auth.permission",
  "pk": 31,
  "fields": {
    "name": "Can delete Клиент",
    "content_type": 8,
    "codename": "delete_client"
  }
},
{
  "model": "auth.permission",
  "pk": 32,
  "fields": {
    "name": "Can view Клиент",
    "content_type": 8,
    "codename": "view_client"
  }
},
{
  "model": "auth.permission",
  "pk": 33,
  "fields": {
    "name": "Can add Тип компании",
    "content_type": 9,
    "codename": "add_companytype"
  }
},
{
  "model": "auth.permission",
  "pk": 34,
  "fields": {
    "name": "Can change Тип компании",
    "content_type": 9,
    "codename": "change_companytype"
  }
},
{
  "model": "auth.permission",
  "pk": 35,
  "fields": {
    "name": "Can delete Тип компании",
    "content_type": 9,
    "codename": "delete_companytype"
  }
},
{
  "model": "auth.permission",
  "pk": 36,
  "fields": {
    "name": "Can view Тип компании",
    "content_type": 9,
    "codename": "view_companytype"
  }
},
{
  "model": "auth.permission",
  "pk": 37,
  "fields": {
    "name": "Can add Страна",
    "content_type": 10,
    "codename": "add_country"
  }
},
{
  "model": "auth.permission",
  "pk": 38,
  "fields": {
    "name": "Can change Страна",
    "content_type": 10,
    "codename": "change_country"
  }
},
{
  "model": "auth.permission",
  "pk": 39,
  "fields": {
    "name": "Can delete Страна",
    "content_type": 10,
    "codename": "delete_country"
  }
},
{
  "model": "auth.permission",
  "pk": 40,
  "fields": {
    "name": "Can view Страна",
    "content_type": 10,
    "codename": "view_country"
  }
},
{
  "model": "auth.permission",
  "pk": 41,
  "fields": {
    "name": "Can add Модель объекта обслуживания",
    "content_type": 11,
    "codename": "add_serviceobjectmodel"
  }
},
{
  "model": "auth.permission",
  "pk": 42,
  "fields": {
    "name": "Can change Модель объекта обслуживания",
    "content_type": 11,
    "codename": "change_serviceobjectmodel"
  }
},
{
  "model": "auth.permission",
  "pk": 43,
  "fields": {
    "name": "Can delete Модель объекта обслуживания",
    "content_type": 11,
    "codename": "delete_serviceobjectmodel"
  }
},
{
  "model": "auth.permission",
  "pk": 44,
  "fields": {
    "name": "Can view Модель объекта обслуживания",
    "content_type": 11,
    "codename": "view_serviceobjectmodel"
  }
},
{
  "model": "auth.permission",
  "pk": 45,
  "fields": {
    "name": "Can add Тип объекта обслуживания",
    "content_type": 12,
    "codename": "add_serviceobjecttype"
  }
},
{
  "model": "auth.permission",
  "pk": 46,
  "fields": {
    "name": "Can change Тип объекта обслуживания",
    "content_type": 12,
    "codename": "change_serviceobjecttype"
  }
},
{
  "model": "auth.permission",
  "pk": 47,
  "fields": {
    "name": "Can delete Тип объекта обслуживания",
    "content_type": 12,
    "codename": "delete_serviceobjecttype"
  }
},
{
  "model": "auth.permission",
  "pk": 48,
  "fields": {
    "name": "Can view Тип объекта обслуживания",
    "content_type": 12,
    "codename": "view_serviceobjecttype"
  }
},
{
  "model": "auth.permission",
  "pk": 49,
  "fields": {
    "name": "Can add Объект обслуживания",
    "content_type": 13,
    "codename": "add_serviceobject"
  }
},
{
  "model": "auth.permission",
  "pk": 50,
  "fields": {
    "name": "Can change Объект обслуживания",
    "content_type": 13,
    "codename": "change_serviceobject"
  }
},
{
  "model": "auth.permission",
  "pk": 51,
  "fields": {
    "name": "Can delete Объект обслуживания",
    "content_type": 13,
    "codename": "delete_serviceobject"
  }
},
{
  "model": "auth.permission",
  "pk": 52,
  "fields": {
    "name": "Can view Объект обслуживания",
    "content_type": 13,
    "codename": "view_serviceobject"
  }
},
{
  "model": "auth.permission",
  "pk": 53,
  "fields": {
    "name": "Can add Должность",
    "content_type": 14,
    "codename": "add_employeeposition"
  }
},
{
  "model": "auth.permission",
  "pk": 54,
  "fields": {
    "name": "Can change Должность",
    "content_type": 14,
    "codename": "change_employeeposition"
  }
},
{
  "model": "auth.permission",
  "pk": 55,
  "fields": {
    "name": "Can delete Должность",
    "content_type": 14,
    "codename": "delete_employeeposition"
  }
},
{
  "model": "auth.permission",
  "pk": 56,
  "fields": {
    "name": "Can view Должность",
    "content_type": 14,
    "codename": "view_employeeposition"
  }
},
{
  "model": "auth.permission",
  "pk": 57,
  "fields": {
    "name": "Can add Приоритет заявки",
    "content_type": 15,
    "codename": "add_ticketpriority"
  }
},
{
  "model": "auth.permission",
  "pk": 58,
  "fields": {
    "name": "Can change Приоритет заявки",
    "content_type": 15,
    "codename": "change_ticketpriority"
  }
},
{
  "model": "auth.permission",
  "pk": 59,
  "fields": {
    "name": "Can delete Приоритет заявки",
    "content_type": 15,
    "codename": "delete_ticketpriority"
  }
},
{
  "model": "auth.permission",
  "pk": 60,
  "fields": {
    "name": "Can view Приоритет заявки",
    "content_type": 15,
    "codename": "view_ticketpriority"
  }
},
{
  "model": "auth.permission",
  "pk": 61,
  "fields": {
    "name": "Can add Статус заявки",
    "content_type": 16,
    "codename": "add_ticketstatus"
  }
},
{
  "model": "auth.permission",
  "pk": 62,
  "fields": {
    "name": "Can change Статус заявки",
    "content_type": 16,
    "codename": "change_ticketstatus"
  }
},
{
  "model": "auth.permission",
  "pk": 63,
  "fields": {
    "name": "Can delete Статус заявки",
    "content_type": 16,
    "codename": "delete_ticketstatus"
  }
},
{
  "model": "auth.permission",
  "pk": 64,
  "fields": {
    "name": "Can view Статус заявки",
    "content_type": 16,
    "codename": "view_ticketstatus"
  }
},
{
  "model": "auth.permission",
  "pk": 65,
  "fields": {
    "name": "Can add Тип заявки",
    "content_type": 17,
    "codename": "add_tickettype"
  }
},
{
  "model": "auth.permission",
  "pk": 66,
  "fields": {
    "name": "Can change Тип заявки",
    "content_type": 17,
    "codename": "change_tickettype"
  }
},
{
  "model": "auth.permission",
  "pk": 67,
  "fields": {
    "name": "Can delete Тип заявки",
    "content_type": 17,
    "codename": "delete_tickettype"
  }
},
{
  "model": "auth.permission",
  "pk": 68,
  "fields": {
    "name": "Can view Тип заявки",
    "content_type": 17,
    "codename": "view_tickettype"
  }
},
{
  "model": "auth.permission",
  "pk": 69,
  "fields": {
    "name": "Can add Работа",
    "content_type": 18,
    "codename": "add_work"
  }
},
{
  "model": "auth.permission",
  "pk": 70,
  "fields": {
    "name": "Can change Работа",
    "content_type": 18,
    "codename": "change_work"
  }
},
{
  "model": "auth.permission",
  "pk": 71,
  "fields": {
    "name": "Can delete Работа",
    "content_type": 18,
    "codename": "delete_work"
  }
},
{
  "model": "auth.permission",
  "pk": 72,
  "fields": {
    "name": "Can view Работа",
    "content_type": 18,
    "codename": "view_work"
  }
},
{
  "model": "auth.permission",
  "pk": 73,
  "fields": {
    "name": "Can add Проблемная область",
    "content_type": 19,
    "codename": "add_problemarea"
  }
},
{
  "model": "auth.permission",
  "pk": 74,
  "fields": {
    "name": "Can change Проблемная область",
    "content_type": 19,
    "codename": "change_problemarea"
  }
},
{
  "model": "auth.permission",
  "pk": 75,
  "fields": {
    "name": "Can delete Проблемная область",
    "content_type": 19,
    "codename": "delete_problemarea"
  }
},
{
  "model": "auth.permission",
  "pk": 76,
  "fields": {
    "name": "Can view Проблемная область",
    "content_type": 19,
    "codename": "view_problemarea"
  }
},
{
  "model": "auth.permission",
  "pk": 77,
  "fields": {
    "name": "Can add Департамент",
    "content_type": 20,
    "codename": "add_department"
  }
},
{
  "model": "auth.permission",
  "pk": 78,
  "fields": {
    "name": "Can change Департамент",
    "content_type": 20,
    "codename": "change_department"
  }
},
{
  "model": "auth.permission",
  "pk": 79,
  "fields": {
    "name": "Can delete Департамент",
    "content_type": 20,
    "codename": "delete_department"
  }
},
{
  "model": "auth.permission",
  "pk": 80,
  "fields": {
    "name": "Can view Департамент",
    "content_type": 20,
    "codename": "view_department"
  }
},
{
  "model": "auth.permission",
  "pk": 81,
  "fields": {
    "name": "Can add Уровень обслуживания",
    "content_type": 21,
    "codename": "add_servicelevel"
  }
},
{
  "model": "auth.permission",
  "pk": 82,
  "fields": {
    "name": "Can change Уровень обслуживания",
    "content_type": 21,
    "codename": "change_servicelevel"
  }
},
{
  "model": "auth.permission",
  "pk": 83,
  "fields": {
    "name": "Can delete Уровень обслуживания",
    "content_type": 21,
    "codename": "delete_servicelevel"
  }
},
{
  "model": "auth.permission",
  "pk": 84,
  "fields": {
    "name": "Can view Уровень обслуживания",
    "content_type": 21,
    "codename": "view_servicelevel"
  }
},
{
  "model": "auth.permission",
  "pk": 85,
  "fields": {
    "name": "Can add Заявка",
    "content_type": 22,
    "codename": "add_ticket"
  }
},
{
  "model": "auth.permission",
  "pk": 86,
  "fields": {
    "name": "Can change Заявка",
    "content_type": 22,
    "codename": "change_ticket"
  }
},
{
  "model": "auth.permission",
  "pk": 87,
  "fields": {
    "name": "Can delete Заявка",
    "content_type": 22,
    "codename": "delete_ticket"
  }
},
{
  "model": "auth.permission",
  "pk": 88,
  "fields": {
    "name": "Can view Заявка",
    "content_type": 22,
    "codename": "view_ticket"
  }
},
{
  "model": "auth.permission",
  "pk": 89,
  "fields": {
    "name": "Может видеть только заявки со статусами Назначенный, На исполнении, Заверщенный",
    "content_type": 22,
    "codename": "see_engineer_tickets"
  }
},
{
  "model": "auth.permission",
  "pk": 90,
  "fields": {
    "name": "Может видеть только заявки со статусами Неопределенный, Подготовленный",
    "content_type": 22,
    "codename": "see_operator_tickets"
  }
},
{
  "model": "auth.permission",
  "pk": 91,
  "fields": {
    "name": "Может видеть только заявки со статусами Подготовленный, Назначенный, Завершенный, Отмененный, На исполнении",
    "content_type": 22,
    "codename": "see_chief_tickets"
  }
},
{
  "model": "auth.permission",
  "pk": 92,
  "fields": {
    "name": "Может закрывать заявки",
    "content_type": 22,
    "codename": "close_ticket"
  }
},
{
  "model": "auth.permission",
  "pk": 93,
  "fields": {
    "name": "Can add Область",
    "content_type": 23,
    "codename": "add_region"
  }
},
{
  "model": "auth.permission",
  "pk": 94,
  "fields": {
    "name": "Can change Область",
    "content_type": 23,
    "codename": "change_region"
  }
},
{
  "model": "auth.permission",
  "pk": 95,
  "fields": {
    "name": "Can delete Область",
    "content_type": 23,
    "codename": "delete_region"
  }
},
{
  "model": "auth.permission",
  "pk": 96,
  "fields": {
    "name": "Can view Область",
    "content_type": 23,
    "codename": "view_region"
  }
},
{
  "model": "auth.permission",
  "pk": 97,
  "fields": {
    "name": "Can add Критерий",
    "content_type": 24,
    "codename": "add_criteriontype"
  }
},
{
  "model": "auth.permission",
  "pk": 98,
  "fields": {
    "name": "Can change Критерий",
    "content_type": 24,
    "codename": "change_criteriontype"
  }
},
{
  "model": "auth.permission",
  "pk": 99,
  "fields": {
    "name": "Can delete Критерий",
    "content_type": 24,
    "codename": "delete_criteriontype"
  }
},
{
  "model": "auth.permission",
  "pk": 100,
  "fields": {
    "name": "Can view Критерий",
    "content_type": 24,
    "codename": "view_criteriontype"
  }
},
{
  "model": "auth.permission",
  "pk": 101,
  "fields": {
    "name": "Can add Договор",
    "content_type": 25,
    "codename": "add_contract"
  }
},
{
  "model": "auth.permission",
  "pk": 102,
  "fields": {
    "name": "Can change Договор",
    "content_type": 25,
    "codename": "change_contract"
  }
},
{
  "model": "auth.permission",
  "pk": 103,
  "fields": {
    "name": "Can delete Договор",
    "content_type": 25,
    "codename": "delete_contract"
  }
},
{
  "model": "auth.permission",
  "pk": 104,
  "fields": {
    "name": "Can view Договор",
    "content_type": 25,
    "codename": "view_contract"
  }
},
{
  "model": "auth.permission",
  "pk": 105,
  "fields": {
    "name": "Can add Тип договора",
    "content_type": 26,
    "codename": "add_contracttype"
  }
},
{
  "model": "auth.permission",
  "pk": 106,
  "fields": {
    "name": "Can change Тип договора",
    "content_type": 26,
    "codename": "change_contracttype"
  }
},
{
  "model": "auth.permission",
  "pk": 107,
  "fields": {
    "name": "Can delete Тип договора",
    "content_type": 26,
    "codename": "delete_contracttype"
  }
},
{
  "model": "auth.permission",
  "pk": 108,
  "fields": {
    "name": "Can view Тип договора",
    "content_type": 26,
    "codename": "view_contracttype"
  }
},
{
  "model": "auth.permission",
  "pk": 109,
  "fields": {
    "name": "Can add Статус договора",
    "content_type": 27,
    "codename": "add_contractstatus"
  }
},
{
  "model": "auth.permission",
  "pk": 110,
  "fields": {
    "name": "Can change Статус договора",
    "content_type": 27,
    "codename": "change_contractstatus"
  }
},
{
  "model": "auth.permission",
  "pk": 111,
  "fields": {
    "name": "Can delete Статус договора",
    "content_type": 27,
    "codename": "delete_contractstatus"
  }
},
{
  "model": "auth.permission",
  "pk": 112,
  "fields": {
    "name": "Can view Статус договора",
    "content_type": 27,
    "codename": "view_contractstatus"
  }
},
{
  "model": "auth.group",
  "pk": 1,
  "fields": {
    "name": "operators",
    "permissions": [
      86,
      90
    ]
  }
},
{
  "model": "auth.group",
  "pk": 2,
  "fields": {
    "name": "chiefs",
    "permissions": [
      86,
      92,
      91
    ]
  }
},
{
  "model": "auth.group",
  "pk": 3,
  "fields": {
    "name": "engineers",
    "permissions": [
      89
    ]
  }
},
{
  "model": "auth.user",
  "pk": 1,
  "fields": {
    "password": "pbkdf2_sha256$320000$MCkPttVbV0QK02EQyOHCED$AfpFsEerxlxVNDNILMzwgiukwIgpY05WP8EFAeQtmgM=",
    "last_login": "2022-05-11T08:25:03.941Z",
    "is_superuser": true,
    "username": "admin",
    "first_name": "",
    "last_name": "",
    "email": "",
    "is_staff": true,
    "is_active": true,
    "date_joined": "2022-04-13T01:46:43Z",
    "groups": [],
    "user_permissions": []
  }
},
{
  "model": "auth.user",
  "pk": 2,
  "fields": {
    "password": "pbkdf2_sha256$320000$uTtwKaM2X7kw5QkN8ttNBY$Xr+tpwp3fEcwmbkO+nyoJdjOV7c68+ibaQ3GSzyRcLk=",
    "last_login": "2022-04-24T17:26:10.433Z",
    "is_superuser": false,
    "username": "moderator",
    "first_name": "Moderator",
    "last_name": "Moderatorov",
    "email": "moderator@gmail.com",
    "is_staff": true,
    "is_active": true,
    "date_joined": "2022-04-16T06:40:50Z",
    "groups": [
      1
    ],
    "user_permissions": []
  }
},
{
  "model": "auth.user",
  "pk": 4,
  "fields": {
    "password": "pbkdf2_sha256$320000$Sch95Gnp3Kp12wmk5wKoRp$a6kooPUdoB4B2yqLu67SMPii59kmuCmN6JjMzCow4SA=",
    "last_login": "2022-05-11T08:25:07.761Z",
    "is_superuser": false,
    "username": "chief",
    "first_name": "",
    "last_name": "",
    "email": "",
    "is_staff": false,
    "is_active": true,
    "date_joined": "2022-04-20T13:35:05Z",
    "groups": [
      2
    ],
    "user_permissions": []
  }
},
{
  "model": "auth.user",
  "pk": 5,
  "fields": {
    "password": "pbkdf2_sha256$320000$H5TW3I6ed4KU8WU7HqNiX5$7NCMciM8cPl54aDwBGH/rgd/BiHUtgOFYqsg9rD9A1c=",
    "last_login": "2022-05-11T08:52:43.643Z",
    "is_superuser": false,
    "username": "engineer",
    "first_name": "",
    "last_name": "",
    "email": "",
    "is_staff": false,
    "is_active": true,
    "date_joined": "2022-04-20T13:35:27Z",
    "groups": [
      3
    ],
    "user_permissions": [
      86
    ]
  }
},
{
  "model": "auth.user",
  "pk": 6,
  "fields": {
    "password": "pbkdf2_sha256$320000$Ke3cZorVrpJ7nNlHU5uWvV$cP+sZzSHaZdk6ffMxK33h57r3GlsjXah6Y2PIwioSo4=",
    "last_login": "2022-05-11T08:11:28.660Z",
    "is_superuser": false,
    "username": "operator",
    "first_name": "",
    "last_name": "",
    "email": "",
    "is_staff": false,
    "is_active": true,
    "date_joined": "2022-04-24T14:21:14Z",
    "groups": [
      1
    ],
    "user_permissions": []
  }
},
{
  "model": "auth.user",
  "pk": 7,
  "fields": {
    "password": "pbkdf2_sha256$320000$5q6hxIfVyxrm4Lh1Y4pEmm$k8nCQmoA2Mab5u2/DwMfcnkMwfFasC5JGxFQpbtS5Ww=",
    "last_login": "2022-05-11T08:52:54.107Z",
    "is_superuser": false,
    "username": "engineer2",
    "first_name": "",
    "last_name": "",
    "email": "",
    "is_staff": false,
    "is_active": true,
    "date_joined": "2022-05-10T12:20:10Z",
    "groups": [
      3
    ],
    "user_permissions": []
  }
}
]
